disklib/__init__.py
disklib/__main__.py
disklib/cli.py
disklib/diskusage.py
disklib/export.py
disklib/path.py
disklib-0.1.4.dist-info/licenses/LICENSE
disklib-0.1.4.dist-info/METADATA
disklib-0.1.4.dist-info/WHEEL
disklib-0.1.4.dist-info/top_level.txt
disklib-0.1.4.dist-info/RECORD
